{
    "InterchangeControl": {
        "CompanyID": "STX",
        "SenderInterchangeIDQualifier": "01",
        "SenderInterchangeID": "056826910",
        "EDIXControlNumber": "59",
        "ReceiverInterchangeIDQualifier": "14",
        "ReceiverInterchangeID": "808368989OT",
        "CreatedDateTime": "20250522191331",
        "AlternateInterchangeNumber": "0",
        "Status": "C05",
        "SenderBranchInterchangeIDQualifier": "",
        "SenderBranchInterchangeID": "",
        "INVEXBranchCode": "132",
        "Errors": [],
        "TransactionSet": [
            {
                "TransactionSetControlNumber": "0001",
                "EDIStandardsOrganizationTransactionSet": "856",
                "EDIStandardsOrganization": "X",
                "ShipmentHeader": [
                    {
                        "TransactionReference": "149-1",
                        "ManifestReference": "149",
                        "VendorShipmentReference": "",
                        "ShippingDateTime": "20250522191335",
                        "EstimatedArrivalDateTime": "20250522191252",
                        "X12TransportationMethod": "E",
                        "CarrierID": "",
                        "CarrierCodeQualifier": "",
                        "CarrierIdentificationCode": "",
                        "CarrierName": "",
                        "CarrierReferenceNumber": "",
                        "VehicleInfo": "",
                        "VehicleLicensePlate": "",
                        "TrailerNumber": "",
                        "TrailerType": "",
                        "TrailerDescription": "",
                        "AppointmentNumber": "",
                        "GateDock": "",
                        "AppointmentDateTime": "00000000000000",
                        "TransportRoute": "-",
                        "RouteDescription": "-",
                        "TermsofTrade": "EXO",
                        "X12ShipmentMethodofPayment": "CC",
                        "MasterGrossWeight": "6436.00",
                        "X12MasterGrossWeightUM": "LB",
                        "NumberofPackages": "1",
                        "GrossWeight": "6436.00",
                        "X12GrossWeightUM": "LB",
                        "NetWeight": "6436.00",
                        "X12NetWeightUM": "LB",
                        "ShipmentQualifier": "",
                        "Item": [
                            {
                                "ReferenceLineNumber": "1",
                                "INVEXReferencePrefix": "SO",
                                "INVEXReferenceNumber": "745",
                                "INVEXReferenceItem": "1",
                                "INVEXReferenceSubItem": "1",
                                "ExternalOrderNumber": "05222025Ron",
                                "ExternalOrderRelease": "",
                                "ExternalOrderDate": "20250522",
                                "ExternalContractNumber": "",
                                "ServiceOrderNumber": "0",
                                "EndUserPO": "",
                                "PartCustomerID": "10000175",
                                "PartNumber": "GVC-60HSG90-.115-15.567-CDM",
                                "PartRevisionNumber": "",
                                "EndUserReferenceLabel1": "End User Label",
                                "EndUserReference1": "",
                                "EndUserReferenceLabel2": "",
                                "EndUserReference2": "",
                                "EndUserReferenceLabel3": "",
                                "EndUserReference3": "",
                                "EndUserReferenceLabel4": "",
                                "EndUserReference4": "",
                                "EndUserReferenceLabel5": "",
                                "EndUserReference5": "",
                                "PartDescription": "",
                                "ProductDescriptionLine1": "GALVANIZED COIL SS GRADE 60 G90",
                                "ProductDescriptionLine2": "CHEM TREAT DRY MIN SPANGLE",
                                "ProductDescriptionLine3": "0.118\" Nom x   15.567\"",
                                "ExtendedFinishDescription":"CHEMTREAT,
DRY,
MINSPANGLE","MultipleDimensionID": "",
                                "DimensionCutBack": "0.0000",
                                "JobSupplyDescription": "",
                                "NumberofPackages": "1",
                                "GrossWeight": "6436.00",
                                "X12GrossWeightUM": "LB",
                                "NetWeight": "6436.00",
                                "X12NetWeightUM": "LB",
                                "ProductItem": [
                                    {
                                        "ItemNumber": "1",
                                        "TagLotID": "3564-1B",
                                        "CustomerTagNo": "CUSTAG123",
                                        "OutsideProcessorTagID": "",
                                        "VendorTagID": "VENTAG456",
                                        "LabelID": "",
                                        "MillOrderNumber": "",
                                        "VendorReference": "ship ref 12345",
                                        "X12PackagingCode": "",
                                        "MaterialClassification": "01",
                                        "MaterialClassificationDatetime": "20250522170432",
                                        "MaterialStatus": "1",
                                        "MaterialStatusDatetime": "20250522170432",
                                        "ReapplicationAction": "N",
                                        "OPSCurrentProcess": "",
                                        "Heat": "RON20250522",
                                        "Form": "GVC",
                                        "Grade": "60SS",
                                        "Size": "118",
                                        "Finish": "G90",
                                        "ExtendedFinishDescription": "",
                                        "SizeDescription": "0.118",
                                        "Density": "0.290400",
                                        "CoilForm": "1",
                                        "Width": "15.5670",
                                        "X12WidthUM": "IN",
                                        "Length": "0.0000",
                                        "X12LengthUM": "IN",
                                        "GaugeSize": "0.11500",
                                        "X12GaugeUM": "ED",
                                        "InnerDiameter": "0.00000",
                                        "X12InnerDiameterUM": "IN",
                                        "OuterDiameter": "0.00000",
                                        "X12OuterDiameterUM": "IN",
                                        "RandomDimension1": "0.0000",
                                        "RandomDimension2": "0.0000",
                                        "RandomDimension3": "0.0000",
                                        "RandomDimension4": "0.0000",
                                        "RandomDimension5": "0.0000",
                                        "RandomDimension6": "0.0000",
                                        "RandomDimension7": "0.0000",
                                        "RandomDimension8": "0.0000",
                                        "RandomArea": "0.0000",
                                        "Weightperpiece": "0.0000",
                                        "Pieces": "1",
                                        "PiecesType": "A",
                                        "Measure": "12379.8900",
                                        "X12MeasureUM": "IN",
                                        "MeasureType": "T",
                                        "MeasureQualifier": "LN",
                                        "Weight": "6436.00",
                                        "X12WeightUM": "LB",
                                        "WeightType": "A",
                                        "NetGrossWeightQualifier": "N",
                                        "CoilLength": "1031.6575",
                                        "X12CoilLengthUM": "FT",
                                        "CoilLengthType": "T",
                                        "CutNumber": "1B",
                                        "CoilInnerDiameter": "20.0000",
                                        "CoilOuterDiameter": "47.0393",
                                        "FaceWidth": "0.0000",
                                        "OriginZoneCountry": "",
                                        "MeltedZone": "",
                                        "MeltedZoneCountry": "",
                                        "ActualWidth1": "0.0000",
                                        "ActualWidth2": "0.0000",
                                        "ActualLength1": "0.0000",
                                        "ActualLength2": "0.0000",
                                        "ActualID1": "0.00000",
                                        "ActualID2": "0.00000",
                                        "ActualOD1": "0.00000",
                                        "ActualOD2": "0.00000",
                                        "ActualGauge1": "0.00000",
                                        "ActualGauge2": "0.00000",
                                        "ActualDiagonal1": "0.0000",
                                        "ActualDiagonal2": "0.0000",
                                        "ActualFlatness1": "0.00000",
                                        "ActualFlatness2": "0.00000",
                                        "ExternalOrderNumber": "05222025Ron",
                                        "ExternalOrderItem": "",
                                        "ExternalOrderRelease": "",
                                        "ExternalOrderDate": "20250522",
                                        "ExternalContractNumber": "",
                                        "EndUserPO": "",
                                        "EndUserReference": "",
                                        "PartCustomerID": "10000175",
                                        "PartNumber": "GVC-60HSG90-.115-15.567-CDM",
                                        "PartRevisionNumber": "",
                                        "PartDescription": "",
                                        "Chemistry": [
                                            {
                                                "LineNumber": "1",
                                                "X12ChemElement": "ZC",
                                                "Value": "0.250000",
                                                "MinValue": "0.000000",
                                                "MaxValue": "0.000000"
                                            },
                                            {
                                                "LineNumber": "2",
                                                "X12ChemElement": "ZMN",
                                                "Value": "1.000000",
                                                "MinValue": "0.000000",
                                                "MaxValue": "0.000000"
                                            },
                                            {
                                                "LineNumber": "3",
                                                "X12ChemElement": "ZP",
                                                "Value": "0.020000",
                                                "MinValue": "0.000000",
                                                "MaxValue": "0.000000"
                                            },
                                            {
                                                "LineNumber": "4",
                                                "X12ChemElement": "ZS",
                                                "Value": "0.020000",
                                                "MinValue": "0.000000",
                                                "MaxValue": "0.000000"
                                            },
                                            {
                                                "LineNumber": "5",
                                                "X12ChemElement": "ZSI",
                                                "Value": "80.000000",
                                                "MinValue": "0.000000",
                                                "MaxValue": "0.000000"
                                            },
                                            {
                                                "LineNumber": "6",
                                                "X12ChemElement": "ZCU",
                                                "Value": "0.200000",
                                                "MinValue": "0.000000",
                                                "MaxValue": "0.000000"
                                            },
                                            {
                                                "LineNumber": "7",
                                                "X12ChemElement": "ZNI",
                                                "Value": "0.200000",
                                                "MinValue": "0.000000",
                                                "MaxValue": "0.000000"
                                            },
                                            {
                                                "LineNumber": "8",
                                                "X12ChemElement": "ZSN",
                                                "Value": "80.000000",
                                                "MinValue": "0.000000",
                                                "MaxValue": "0.000000"
                                            },
                                            {
                                                "LineNumber": "9",
                                                "X12ChemElement": "ZCR",
                                                "Value": "0.100000",
                                                "MinValue": "0.000000",
                                                "MaxValue": "0.000000"
                                            },
                                            {
                                                "LineNumber": "10",
                                                "X12ChemElement": "ZMO",
                                                "Value": "0.050000",
                                                "MinValue": "0.000000",
                                                "MaxValue": "0.000000"
                                            },
                                            {
                                                "LineNumber": "11",
                                                "X12ChemElement": "ZAL",
                                                "Value": "80.000000",
                                                "MinValue": "0.000000",
                                                "MaxValue": "0.000000"
                                            },
                                            {
                                                "LineNumber": "12",
                                                "X12ChemElement": "ZV",
                                                "Value": "0.007000",
                                                "MinValue": "0.000000",
                                                "MaxValue": "0.000000"
                                            },
                                            {
                                                "LineNumber": "13",
                                                "X12ChemElement": "ZN",
                                                "Value": "80.000000",
                                                "MinValue": "0.000000",
                                                "MaxValue": "0.000000"
                                            },
                                            {
                                                "LineNumber": "14",
                                                "X12ChemElement": "ZNB",
                                                "Value": "0.007000",
                                                "MinValue": "0.000000",
                                                "MaxValue": "0.000000"
                                            },
                                            {
                                                "LineNumber": "15",
                                                "X12ChemElement": "ZTI",
                                                "Value": "0.020000",
                                                "MinValue": "0.000000",
                                                "MaxValue": "0.000000"
                                            },
                                            {
                                                "LineNumber": "16",
                                                "X12ChemElement": "ZB",
                                                "Value": "75.000000",
                                                "MinValue": "0.000000",
                                                "MaxValue": "0.000000"
                                            },
                                            {
                                                "LineNumber": "17",
                                                "X12ChemElement": "ZCA",
                                                "Value": "75.000000",
                                                "MinValue": "0.000000",
                                                "MaxValue": "0.000000"
                                            }
                                        ],
                                        "Damages": [],
                                        "ProductItemInstructions": [],
                                        "NameAndAddress": []
                                    }
                                ],
                                "ItemInstructions": [
                                    {
                                        "INVEXInstructionType": "55",
                                        "Text": "One 1-1/4? Belly Band \nTwo 1-1/4? ID to OD Bands \nThree 1-1/4? Cluster Bands \n \n?Mark cuts as Left-Center-Right?"
                                    }
                                ]
                            }
                        ],
                        "HeaderInstructions": [],
                        "HeaderNameAddress": [
                            {
                                "AddressType": "F",
                                "IdentificationCodeQualifier": "93",
                                "IdentificationCode": "832061845",
                                "NameLine1": "SANTA TERESA",
                                "NameLine2": "",
                                "AddressLine1": "175 Kittyhawk Blvd.",
                                "AddressLine2": "",
                                "AddressLine3": "",
                                "City": "SANTA TERESA",
                                "PostalCode": "88008",
                                "CountryCode": "USA",
                                "StateProvincecode": "NM",
                                "TelAreaCode": "574",
                                "TelNumber": "3788989",
                                "TelExtension": "",
                                "FaxAreaCode": "",
                                "FaxNumber": "",
                                "FaxExtension": ""
                            },
                            {
                                "AddressType": "O",
                                "IdentificationCodeQualifier": "14",
                                "IdentificationCode": "808368989OT",
                                "NameLine1": "Nucor Steel Gallatin LLC",
                                "NameLine2": "",
                                "AddressLine1": "4831 US Hwy 42",
                                "AddressLine2": "",
                                "AddressLine3": "",
                                "City": "West Ghent",
                                "PostalCode": "41045",
                                "CountryCode": "USA",
                                "StateProvincecode": "KY",
                                "TelAreaCode": "",
                                "TelNumber": "",
                                "TelExtension": "",
                                "FaxAreaCode": "",
                                "FaxNumber": "",
                                "FaxExtension": ""
                            },
                            {
                                "AddressType": "S",
                                "IdentificationCodeQualifier": "1",
                                "IdentificationCode": "808368989",
                                "NameLine1": "Nucor Steel Gallatin LLC",
                                "NameLine2": "",
                                "AddressLine1": "3030 Dulles Dr",
                                "AddressLine2": "",
                                "AddressLine3": "",
                                "City": "Mira Loma",
                                "PostalCode": "91752",
                                "CountryCode": "USA",
                                "StateProvincecode": "CA",
                                "TelAreaCode": "",
                                "TelNumber": "",
                                "TelExtension": "",
                                "FaxAreaCode": "",
                                "FaxNumber": "",
                                "FaxExtension": ""
                            }
                        ]
                    }
                ]
            }
        ]
    }
}